reachy_mini_dances_library/__init__.py
reachy_mini_dances_library/dance_move.py
reachy_mini_dances_library/rhythmic_motion.py
reachy_mini_dances_library/collection/__init__.py
reachy_mini_dances_library/collection/dance.py
reachy_mini_dances_library/collection/forbidden.py
reachy_mini_dances_library-0.2.1.dist-info/METADATA
reachy_mini_dances_library-0.2.1.dist-info/WHEEL
reachy_mini_dances_library-0.2.1.dist-info/top_level.txt
reachy_mini_dances_library-0.2.1.dist-info/RECORD
