Metadata-Version: 2.4
Name: reachy_mini_dances_library
Version: 0.2.1
Author-email: Pollen Robotics <contact@pollen-robotics.com>
Requires-Python: >=3.8
Requires-Dist: reachy_mini
Provides-Extra: dev
Requires-Dist: pytest; extra == "dev"
Requires-Dist: ruff==0.12.0; extra == "dev"
